melo/__init__.py
melo/api.py
melo/app.py
melo/attentions.py
melo/commons.py
melo/data_utils.py
melo/download_utils.py
melo/infer.py
melo/init_downloads.py
melo/losses.py
melo/main.py
melo/mel_processing.py
melo/models.py
melo/modules.py
melo/preprocess_text.py
melo/split_utils.py
melo/train.py
melo/transforms.py
melo/utils.py
melo/monotonic_align/__init__.py
melo/monotonic_align/core.py
melo/text/__init__.py
melo/text/chinese.py
melo/text/chinese_bert.py
melo/text/chinese_mix.py
melo/text/cleaner.py
melo/text/cleaner_multiling.py
melo/text/cmudict_cache.pickle
melo/text/english.py
melo/text/english_bert.py
melo/text/french.py
melo/text/french_bert.py
melo/text/japanese.py
melo/text/japanese_bert.py
melo/text/ko_dictionary.py
melo/text/korean.py
melo/text/opencpop-strict.txt
melo/text/spanish.py
melo/text/spanish_bert.py
melo/text/symbols.py
melo/text/tone_sandhi.py
melo/text/english_utils/__init__.py
melo/text/english_utils/abbreviations.py
melo/text/english_utils/number_norm.py
melo/text/english_utils/time_norm.py
melo/text/es_phonemizer/__init__.py
melo/text/es_phonemizer/base.py
melo/text/es_phonemizer/cleaner.py
melo/text/es_phonemizer/es_symbols.txt
melo/text/es_phonemizer/es_to_ipa.py
melo/text/es_phonemizer/example_ipa.txt
melo/text/es_phonemizer/gruut_wrapper.py
melo/text/es_phonemizer/punctuation.py
melo/text/es_phonemizer/spanish_symbols.txt
melo/text/fr_phonemizer/__init__.py
melo/text/fr_phonemizer/base.py
melo/text/fr_phonemizer/cleaner.py
melo/text/fr_phonemizer/example_ipa.txt
melo/text/fr_phonemizer/fr_to_ipa.py
melo/text/fr_phonemizer/french_abbreviations.py
melo/text/fr_phonemizer/french_symbols.txt
melo/text/fr_phonemizer/gruut_wrapper.py
melo/text/fr_phonemizer/punctuation.py
melotts_krqnf-0.1.2.dist-info/licenses/LICENSE
melotts_krqnf-0.1.2.dist-info/METADATA
melotts_krqnf-0.1.2.dist-info/WHEEL
melotts_krqnf-0.1.2.dist-info/entry_points.txt
melotts_krqnf-0.1.2.dist-info/top_level.txt
melotts_krqnf-0.1.2.dist-info/RECORD
